browser_signals/__init__.py
browser_signals/core.py
browser_signals/pytest_plugin.py
browser_signals-0.1.0.dist-info/METADATA
browser_signals-0.1.0.dist-info/WHEEL
browser_signals-0.1.0.dist-info/entry_points.txt
browser_signals-0.1.0.dist-info/licenses/LICENSE
browser_signals-0.1.0.dist-info/RECORD
