Metadata-Version: 2.4
Name: browser-signals
Version: 0.1.0
Summary: Non-blocking visual signals (banners/flash) for Selenium runs; optional pytest auto-annotation.
Project-URL: Homepage, https://github.com/aabdullah-bos/browser-signals
Project-URL: Repository, https://github.com/aabdullah-bos/browser-signals.git
Project-URL: Issues, https://github.com/aabdullah-bos/browser-signals/issues
Author-email: Aquil Abdullah <aquil@aquilabdullah.com>
License: MIT
License-File: LICENSE
Keywords: ci,debugging,pytest,selenium,testing,xvfb
Classifier: License :: OSI Approved :: MIT License
Classifier: Programming Language :: Python :: 3
Classifier: Programming Language :: Python :: 3 :: Only
Classifier: Programming Language :: Python :: 3.8
Classifier: Programming Language :: Python :: 3.9
Classifier: Programming Language :: Python :: 3.10
Classifier: Programming Language :: Python :: 3.11
Classifier: Programming Language :: Python :: 3.12
Classifier: Topic :: Software Development :: Testing
Requires-Python: >=3.8
Provides-Extra: pytest
Requires-Dist: pytest>=7.0; extra == 'pytest'
Provides-Extra: selenium
Requires-Dist: selenium>=4.10; extra == 'selenium'
Requires-Dist: webdriver-manager>=4.0; extra == 'selenium'
